pjsekai/scores/__init__.py
pjsekai/scores/__main__.py
pjsekai/scores/drawing.py
pjsekai/scores/line.py
pjsekai/scores/lyric.py
pjsekai/scores/meta.py
pjsekai/scores/rebase.py
pjsekai/scores/score.py
pjsekai/scores/css/default.css
pjsekai/scores/notes/__init__.py
pjsekai/scores/notes/base.py
pjsekai/scores/notes/directional.py
pjsekai/scores/notes/event.py
pjsekai/scores/notes/note.py
pjsekai/scores/notes/slide.py
pjsekai/scores/notes/tap.py
pjsekai/scores/types/__init__.py
pjsekai/scores/types/fraction.py
pjsekai.scores-0.1.10.dist-info/LICENSE
pjsekai.scores-0.1.10.dist-info/METADATA
pjsekai.scores-0.1.10.dist-info/WHEEL
pjsekai.scores-0.1.10.dist-info/top_level.txt
pjsekai.scores-0.1.10.dist-info/RECORD
