Metadata-Version: 2.1
Name: pjsekai.scores
Version: 0.1.10
Summary: Render Project Sekai score files (sus) to images (svg). 
Author-email: Amaoto <amaoto@pjsekai.moe>
License: MIT License
Project-URL: Homepage, https://gitlab.com/pjsekai/scores
Project-URL: Documentation, https://gitlab.com/pjsekai/scores/-/wikis
Project-URL: Bug Tracker, https://gitlab.com/pjsekai/scores/-/issues
Keywords: Project Sekai,pjsekai,SUS
Classifier: Programming Language :: Python :: 3
Classifier: License :: OSI Approved :: MIT License
Classifier: Operating System :: OS Independent
Requires-Python: >=3.10
License-File: LICENSE
Requires-Dist: svgwrite
